url_filter/__init__.py
url_filter/constants.py
url_filter/exceptions.py
url_filter/fields.py
url_filter/filters.py
url_filter/utils.py
url_filter/validators.py
url_filter/backends/__init__.py
url_filter/backends/base.py
url_filter/backends/django.py
url_filter/backends/plain.py
url_filter/backends/sqlalchemy.py
url_filter/filtersets/__init__.py
url_filter/filtersets/base.py
url_filter/filtersets/django.py
url_filter/filtersets/plain.py
url_filter/filtersets/sqlalchemy.py
url_filter/integrations/__init__.py
url_filter/integrations/drf.py
url_filter/integrations/drf_coreapi.py
drf_url_filter-0.3.15.dist-info/AUTHORS.rst
drf_url_filter-0.3.15.dist-info/LICENSE.rst
drf_url_filter-0.3.15.dist-info/METADATA
drf_url_filter-0.3.15.dist-info/WHEEL
drf_url_filter-0.3.15.dist-info/top_level.txt
drf_url_filter-0.3.15.dist-info/RECORD
